Metadata-Version: 1.0
Name: marshmallow-numpy
Version: 0.2.0
Summary: Marshmallow numpy field
Home-page: UNKNOWN
Author: Shachak Zicher
Author-email: shachakz12@gmail.com
License: MIT
Platform: UNKNOWN
